mlsysops_cli/__init__.py
mlsysops_cli/cli.py
mlsysops_cli/deployment/__init__.py
mlsysops_cli/deployment/api-service-deployment.yaml
mlsysops_cli/deployment/cluster-agents-daemonset.yaml
mlsysops_cli/deployment/cluster-propagation-policy.yaml
mlsysops_cli/deployment/continuum-agent-daemonset.yaml
mlsysops_cli/deployment/create_descriptions.py
mlsysops_cli/deployment/deploy.py
mlsysops_cli/deployment/descriptions_util.py
mlsysops_cli/deployment/ejabberd-deployment.yaml
mlsysops_cli/deployment/mlsysops-rbac.yaml
mlsysops_cli/deployment/namespace.yaml
mlsysops_cli/deployment/node-agents-daemonset.yaml
mlsysops_cli/deployment/propagation-policy.yaml
mlsysops_cli/deployment/redis-stack-deployment.yaml
mlsysops_cli/templates/app.yaml.j2
mlsysops_cli/templates/cluster.yaml.j2
mlsysops_cli/templates/continuum.yaml.j2
mlsysops_cli/templates/node.yaml.j2
mlsysops_cli-0.1.11.dist-info/licenses/LICENSE
mlsysops_cli-0.1.11.dist-info/METADATA
mlsysops_cli-0.1.11.dist-info/WHEEL
mlsysops_cli-0.1.11.dist-info/entry_points.txt
mlsysops_cli-0.1.11.dist-info/top_level.txt
mlsysops_cli-0.1.11.dist-info/RECORD
