Metadata-Version: 2.4
Name: mlsysops-cli
Version: 0.1.11
Summary: The MLSysOps Agents Framework CLI.
Home-page: https://github.com/mlsysops-project/mlsysops-framework
Author: MLSysOps Project Consortium
Author-email: info@mlsysops.eu
License: Apache License 2.0
Classifier: Development Status :: 3 - Alpha
Classifier: Intended Audience :: Developers
Classifier: Programming Language :: Python :: 3
Classifier: Programming Language :: Python :: 3.10
License-File: LICENSE
Requires-Dist: click>=8.0
Requires-Dist: requests>=2.25
Requires-Dist: PyYAML>=5.4
Requires-Dist: ruamel.yaml>=0.17
Requires-Dist: kubernetes>=26.1.0
Requires-Dist: jinja2>=3.1
Dynamic: author
Dynamic: author-email
Dynamic: classifier
Dynamic: description
Dynamic: description-content-type
Dynamic: home-page
Dynamic: license
Dynamic: license-file
Dynamic: requires-dist
Dynamic: summary
